imagepypelines/Logger.py
imagepypelines/__init__.py
imagepypelines/version_info.py
imagepypelines/core/Block.py
imagepypelines/core/Data.py
imagepypelines/core/Exceptions.py
imagepypelines/core/Pipeline.py
imagepypelines/core/__init__.py
imagepypelines/core/arg_checking.py
imagepypelines/core/block_subclasses.py
imagepypelines/core/caching.py
imagepypelines/core/constants.py
imagepypelines/core/img_tools.py
imagepypelines/core/imports.py
imagepypelines/core/io_tools.py
imagepypelines/core/ml_tools.py
imagepypelines/core/pipeline_tools.py
imagepypelines/core/util.py
imagepypelines/data/00001.png
imagepypelines/data/00102.png
imagepypelines/data/standard_images/carlenna.png
imagepypelines/data/standard_images/crowd.jpg
imagepypelines/data/standard_images/gecko.jpg
imagepypelines/data/standard_images/giza.jpg
imagepypelines/data/standard_images/lenna.tif
imagepypelines/data/standard_images/lenna_gray.tif
imagepypelines/data/standard_images/linear.tif
imagepypelines/data/standard_images/panda.jpg
imagepypelines/data/standard_images/panda_color.jpg
imagepypelines/data/standard_images/pig.jpg
imagepypelines/data/standard_images/redhat.ppm
imagepypelines/data/standard_images/roger.jpg
imagepypelines/data/standard_images/sparse_checkerboard.tif
tests/__init__.py
tests/graphing_test.py
tests/test_builtin_blocks.py
tests/test_builtin_pipelines.py
tests/test_core.py
tests/test_io.py
tests/test_ml.py
tests/test_serialization.py
tests/test_util.py
imagepypelines-0.3.0a0.dist-info/LICENSE
imagepypelines-0.3.0a0.dist-info/METADATA
imagepypelines-0.3.0a0.dist-info/WHEEL
imagepypelines-0.3.0a0.dist-info/top_level.txt
imagepypelines-0.3.0a0.dist-info/RECORD
